swyft/__init__.py
swyft/__version__.py
swyft/types.py
swyft/lightning/__init__.py
swyft/lightning/bounds.py
swyft/lightning/core.py
swyft/lightning/data.py
swyft/lightning/estimators.py
swyft/lightning/online.py
swyft/lightning/simulator.py
swyft/lightning/torchstore.py
swyft/lightning/utils.py
swyft/networks/__init__.py
swyft/networks/channelized.py
swyft/networks/classifier.py
swyft/networks/standardization.py
swyft/plot/__init__.py
swyft/plot/mass.py
swyft/plot/plot.py
swyft/utils/__init__.py
swyft/utils/array.py
swyft/utils/marginals.py
swyft/utils/misc.py
tests/__init__.py
tests/test_simulator.py
swyft-0.4.5.dist-info/AUTHORS
swyft-0.4.5.dist-info/LICENSE
swyft-0.4.5.dist-info/METADATA
swyft-0.4.5.dist-info/WHEEL
swyft-0.4.5.dist-info/top_level.txt
swyft-0.4.5.dist-info/RECORD
