Metadata-Version: 2.1
Name: swyft
Version: 0.4.5
Summary: Universal scalable simulation-based inference with TMNRE (Truncated Marginal Neural Ratio Estimation) and pytorch-lightning.
Home-page: https://github.com/undark-lab/swyft
License: MIT License
Classifier: Development Status :: 3 - Alpha
Classifier: Programming Language :: Python :: 3
Classifier: Programming Language :: Python :: 3.7
Classifier: Programming Language :: Python :: 3.8
Classifier: Programming Language :: Python :: 3.9
Classifier: Programming Language :: Python :: 3.10
Classifier: Environment :: GPU
Classifier: Operating System :: OS Independent
Classifier: Operating System :: POSIX
Classifier: License :: OSI Approved :: MIT License
Requires-Python: >=3.7
License-File: LICENSE
License-File: AUTHORS
Requires-Dist: toolz >=0.10.0
Requires-Dist: numpy >=1.18.1
Requires-Dist: torch >=1.10.2
Requires-Dist: pytorch-lightning <=1.9.5,>=1.5.10
Requires-Dist: zarr >=2.5.0
Requires-Dist: matplotlib >=3.1.3
Requires-Dist: scipy >=1.4.1
Requires-Dist: torchist >=0.1.7
Requires-Dist: fasteners >=0.17
Provides-Extra: dev
Requires-Dist: pre-commit ; extra == 'dev'
Requires-Dist: black ; extra == 'dev'
Requires-Dist: isort ; extra == 'dev'
Requires-Dist: pytest ; extra == 'dev'
Provides-Extra: docs
Requires-Dist: sphinx ; extra == 'docs'
Requires-Dist: sphinxcontrib-bibtex ; extra == 'docs'
Requires-Dist: nbsphinx ; extra == 'docs'
Requires-Dist: nbsphinx-link ; extra == 'docs'
Requires-Dist: ipykernel ; extra == 'docs'
Requires-Dist: furo ; extra == 'docs'
